<?xml version="1.0" encoding="utf-8"?>
<VugenScriptMetadata>
  <ScriptName>Script1</ScriptName>
  <Protocol>Web - HTTP/HTML</Protocol>
  <ActionFiles>
    <FileEntry Name="vuser_init.c" Filter="2" />
    <FileEntry Name="Action.c" Filter="2" />
    <FileEntry Name="vuser_end.c" Filter="2" />
  </ActionFiles>
  <GeneralFiles>
    <FileEntry Name="Script1.usr" Filter="4" />
    <FileEntry Name="default.cfg" Filter="4" />
    <FileEntry Name="default.usp" Filter="4" />
    <FileEntry Name="Script1.prm" Filter="2" />
    <FileEntry Name="globals.h" Filter="2" />
    <FileEntry Name="Class.dat" Filter="2" />
    <FileEntry Name="Login.dat" Filter="2" />
    <FileEntry Name="City_1.dat" Filter="2" />
    <FileEntry Name="City_2.dat" Filter="2" />
    <FileEntry Name="Sit.dat" Filter="2" />
    <FileEntry Name="combined_Script1.c" Filter="2" />
    <FileEntry Name="pre_cci.c" Filter="2" />
    <FileEntry Name="124827512440.idx" Filter="1" />
    <FileEntry Name="133012554440.idx" Filter="1" />
    <FileEntry Name="13301255444_05P.547.idx" Filter="1" />
    <FileEntry Name="13301255444_0qH.885.idx" Filter="1" />
    <FileEntry Name="13301255444_0Uc.639.idx" Filter="1" />
    <FileEntry Name="13301255444_1IG.355.idx" Filter="1" />
    <FileEntry Name="13301255444_1Kt.113.idx" Filter="1" />
    <FileEntry Name="13301255444_1pD.593.idx" Filter="1" />
    <FileEntry Name="13301255444_1UP.1.idx" Filter="1" />
    <FileEntry Name="13301255444_2nd.213.idx" Filter="1" />
    <FileEntry Name="13301255444_2tw.579.idx" Filter="1" />
    <FileEntry Name="13301255444_2W2.773.idx" Filter="1" />
    <FileEntry Name="13301255444_4BL.619.idx" Filter="1" />
    <FileEntry Name="13301255444_4R7.653.idx" Filter="1" />
    <FileEntry Name="13301255444_4rF.279.idx" Filter="1" />
    <FileEntry Name="13301255444_4uN.257.idx" Filter="1" />
    <FileEntry Name="13301255444_53K.85.idx" Filter="1" />
    <FileEntry Name="13301255444_58X.187.idx" Filter="1" />
    <FileEntry Name="13301255444_5aH.339.idx" Filter="1" />
    <FileEntry Name="13301255444_5aJ.137.idx" Filter="1" />
    <FileEntry Name="13301255444_5cf.151.idx" Filter="1" />
    <FileEntry Name="13301255444_5jD.57.idx" Filter="1" />
    <FileEntry Name="13301255444_68Q.189.idx" Filter="1" />
    <FileEntry Name="13301255444_6kr.789.idx" Filter="1" />
    <FileEntry Name="13301255444_6qH.181.idx" Filter="1" />
    <FileEntry Name="13301255444_70d.725.idx" Filter="1" />
    <FileEntry Name="13301255444_7gQ.931.idx" Filter="1" />
    <FileEntry Name="13301255444_7Rq.51.idx" Filter="1" />
    <FileEntry Name="13301255444_7YY.951.idx" Filter="1" />
    <FileEntry Name="13301255444_8HJ.69.idx" Filter="1" />
    <FileEntry Name="13301255444_8Jx.825.idx" Filter="1" />
    <FileEntry Name="13301255444_8QA.499.idx" Filter="1" />
    <FileEntry Name="13301255444_8rW.873.idx" Filter="1" />
    <FileEntry Name="13301255444_9e5.295.idx" Filter="1" />
    <FileEntry Name="13301255444_9S4.11.idx" Filter="1" />
    <FileEntry Name="13301255444_9SZ.437.idx" Filter="1" />
    <FileEntry Name="13301255444_A31.71.idx" Filter="1" />
    <FileEntry Name="13301255444_a3D.255.idx" Filter="1" />
    <FileEntry Name="13301255444_a6h.207.idx" Filter="1" />
    <FileEntry Name="13301255444_a9I.501.idx" Filter="1" />
    <FileEntry Name="13301255444_AHY.477.idx" Filter="1" />
    <FileEntry Name="13301255444_AKr.349.idx" Filter="1" />
    <FileEntry Name="13301255444_ATl.335.idx" Filter="1" />
    <FileEntry Name="13301255444_aw6.757.idx" Filter="1" />
    <FileEntry Name="13301255444_b2q.45.idx" Filter="1" />
    <FileEntry Name="13301255444_B4R.311.idx" Filter="1" />
    <FileEntry Name="13301255444_b4u.321.idx" Filter="1" />
    <FileEntry Name="13301255444_BAi.529.idx" Filter="1" />
    <FileEntry Name="13301255444_bcl.391.idx" Filter="1" />
    <FileEntry Name="13301255444_bFV.689.idx" Filter="1" />
    <FileEntry Name="13301255444_BVZ.5.idx" Filter="1" />
    <FileEntry Name="13301255444_bZY.893.idx" Filter="1" />
    <FileEntry Name="13301255444_CFp.285.idx" Filter="1" />
    <FileEntry Name="13301255444_chL.575.idx" Filter="1" />
    <FileEntry Name="13301255444_cK8.205.idx" Filter="1" />
    <FileEntry Name="13301255444_COb.173.idx" Filter="1" />
    <FileEntry Name="13301255444_D6M.935.idx" Filter="1" />
    <FileEntry Name="13301255444_DaG.921.idx" Filter="1" />
    <FileEntry Name="13301255444_dJj.839.idx" Filter="1" />
    <FileEntry Name="13301255444_dPl.179.idx" Filter="1" />
    <FileEntry Name="13301255444_DUM.57.idx" Filter="1" />
    <FileEntry Name="13301255444_Ebk.499.idx" Filter="1" />
    <FileEntry Name="13301255444_ECe.781.idx" Filter="1" />
    <FileEntry Name="13301255444_EnO.359.idx" Filter="1" />
    <FileEntry Name="13301255444_euj.129.idx" Filter="1" />
    <FileEntry Name="13301255444_ev9.173.idx" Filter="1" />
    <FileEntry Name="13301255444_evX.299.idx" Filter="1" />
    <FileEntry Name="13301255444_FF3.775.idx" Filter="1" />
    <FileEntry Name="13301255444_fGK.13.idx" Filter="1" />
    <FileEntry Name="13301255444_Fnf.549.idx" Filter="1" />
    <FileEntry Name="13301255444_fO7.837.idx" Filter="1" />
    <FileEntry Name="13301255444_fPH.647.idx" Filter="1" />
    <FileEntry Name="13301255444_fPV.557.idx" Filter="1" />
    <FileEntry Name="13301255444_g4i.833.idx" Filter="1" />
    <FileEntry Name="13301255444_gal.775.idx" Filter="1" />
    <FileEntry Name="13301255444_Gbs.321.idx" Filter="1" />
    <FileEntry Name="13301255444_GeD.971.idx" Filter="1" />
    <FileEntry Name="13301255444_GKb.11.idx" Filter="1" />
    <FileEntry Name="13301255444_GM0.285.idx" Filter="1" />
    <FileEntry Name="13301255444_GNu.297.idx" Filter="1" />
    <FileEntry Name="13301255444_gOc.265.idx" Filter="1" />
    <FileEntry Name="13301255444_gOl.441.idx" Filter="1" />
    <FileEntry Name="13301255444_GpZ.597.idx" Filter="1" />
    <FileEntry Name="13301255444_GrQ.339.idx" Filter="1" />
    <FileEntry Name="13301255444_gUR.455.idx" Filter="1" />
    <FileEntry Name="13301255444_GUY.635.idx" Filter="1" />
    <FileEntry Name="13301255444_H07.517.idx" Filter="1" />
    <FileEntry Name="13301255444_HM0.5.idx" Filter="1" />
    <FileEntry Name="13301255444_HQW.55.idx" Filter="1" />
    <FileEntry Name="13301255444_HsX.523.idx" Filter="1" />
    <FileEntry Name="13301255444_Hvj.427.idx" Filter="1" />
    <FileEntry Name="13301255444_hWE.875.idx" Filter="1" />
    <FileEntry Name="13301255444_hxP.377.idx" Filter="1" />
    <FileEntry Name="13301255444_Hza.569.idx" Filter="1" />
    <FileEntry Name="13301255444_HZc.507.idx" Filter="1" />
    <FileEntry Name="13301255444_I1g.707.idx" Filter="1" />
    <FileEntry Name="13301255444_iB2.563.idx" Filter="1" />
    <FileEntry Name="13301255444_Inx.337.idx" Filter="1" />
    <FileEntry Name="13301255444_J0H.751.idx" Filter="1" />
    <FileEntry Name="13301255444_j3W.297.idx" Filter="1" />
    <FileEntry Name="13301255444_j7j.423.idx" Filter="1" />
    <FileEntry Name="13301255444_jcw.193.idx" Filter="1" />
    <FileEntry Name="13301255444_JSY.15.idx" Filter="1" />
    <FileEntry Name="13301255444_JWA.113.idx" Filter="1" />
    <FileEntry Name="13301255444_jZ6.253.idx" Filter="1" />
    <FileEntry Name="13301255444_K2w.457.idx" Filter="1" />
    <FileEntry Name="13301255444_k81.383.idx" Filter="1" />
    <FileEntry Name="13301255444_K8s.363.idx" Filter="1" />
    <FileEntry Name="13301255444_KCB.209.idx" Filter="1" />
    <FileEntry Name="13301255444_khl.91.idx" Filter="1" />
    <FileEntry Name="13301255444_ki2.899.idx" Filter="1" />
    <FileEntry Name="13301255444_KiC.95.idx" Filter="1" />
    <FileEntry Name="13301255444_Kyv.577.idx" Filter="1" />
    <FileEntry Name="13301255444_Kz7.927.idx" Filter="1" />
    <FileEntry Name="13301255444_L5e.33.idx" Filter="1" />
    <FileEntry Name="13301255444_LaP.639.idx" Filter="1" />
    <FileEntry Name="13301255444_LdL.263.idx" Filter="1" />
    <FileEntry Name="13301255444_Let.213.idx" Filter="1" />
    <FileEntry Name="13301255444_lFi.603.idx" Filter="1" />
    <FileEntry Name="13301255444_lg4.819.idx" Filter="1" />
    <FileEntry Name="13301255444_lIF.653.idx" Filter="1" />
    <FileEntry Name="13301255444_LjR.783.idx" Filter="1" />
    <FileEntry Name="13301255444_lJx.177.idx" Filter="1" />
    <FileEntry Name="13301255444_Lkh.639.idx" Filter="1" />
    <FileEntry Name="13301255444_LNC.957.idx" Filter="1" />
    <FileEntry Name="13301255444_LTp.731.idx" Filter="1" />
    <FileEntry Name="13301255444_MCE.231.idx" Filter="1" />
    <FileEntry Name="13301255444_Mf5.873.idx" Filter="1" />
    <FileEntry Name="13301255444_NJv.387.idx" Filter="1" />
    <FileEntry Name="13301255444_nJX.759.idx" Filter="1" />
    <FileEntry Name="13301255444_NNf.33.idx" Filter="1" />
    <FileEntry Name="13301255444_Nq0.625.idx" Filter="1" />
    <FileEntry Name="13301255444_NQJ.513.idx" Filter="1" />
    <FileEntry Name="13301255444_Nsc.587.idx" Filter="1" />
    <FileEntry Name="13301255444_O0S.49.idx" Filter="1" />
    <FileEntry Name="13301255444_o0x.995.idx" Filter="1" />
    <FileEntry Name="13301255444_o8g.805.idx" Filter="1" />
    <FileEntry Name="13301255444_oaX.155.idx" Filter="1" />
    <FileEntry Name="13301255444_ORN.189.idx" Filter="1" />
    <FileEntry Name="13301255444_oyI.395.idx" Filter="1" />
    <FileEntry Name="13301255444_oYQ.919.idx" Filter="1" />
    <FileEntry Name="13301255444_PPI.87.idx" Filter="1" />
    <FileEntry Name="13301255444_pWc.307.idx" Filter="1" />
    <FileEntry Name="13301255444_Q2b.941.idx" Filter="1" />
    <FileEntry Name="13301255444_Q2M.179.idx" Filter="1" />
    <FileEntry Name="13301255444_qdn.523.idx" Filter="1" />
    <FileEntry Name="13301255444_qMF.847.idx" Filter="1" />
    <FileEntry Name="13301255444_Qt9.389.idx" Filter="1" />
    <FileEntry Name="13301255444_QuR.415.idx" Filter="1" />
    <FileEntry Name="13301255444_QXf.35.idx" Filter="1" />
    <FileEntry Name="13301255444_r4b.217.idx" Filter="1" />
    <FileEntry Name="13301255444_R71.267.idx" Filter="1" />
    <FileEntry Name="13301255444_r8P.23.idx" Filter="1" />
    <FileEntry Name="13301255444_rh6.613.idx" Filter="1" />
    <FileEntry Name="13301255444_rlK.557.idx" Filter="1" />
    <FileEntry Name="13301255444_RSF.799.idx" Filter="1" />
    <FileEntry Name="13301255444_ruk.957.idx" Filter="1" />
    <FileEntry Name="13301255444_sGR.183.idx" Filter="1" />
    <FileEntry Name="13301255444_sI5.603.idx" Filter="1" />
    <FileEntry Name="13301255444_sRx.783.idx" Filter="1" />
    <FileEntry Name="13301255444_SW2.189.idx" Filter="1" />
    <FileEntry Name="13301255444_Teo.823.idx" Filter="1" />
    <FileEntry Name="13301255444_TrL.213.idx" Filter="1" />
    <FileEntry Name="13301255444_trR.835.idx" Filter="1" />
    <FileEntry Name="13301255444_txz.891.idx" Filter="1" />
    <FileEntry Name="13301255444_TZt.157.idx" Filter="1" />
    <FileEntry Name="13301255444_UaH.349.idx" Filter="1" />
    <FileEntry Name="13301255444_Ual.607.idx" Filter="1" />
    <FileEntry Name="13301255444_uGa.955.idx" Filter="1" />
    <FileEntry Name="13301255444_URR.547.idx" Filter="1" />
    <FileEntry Name="13301255444_us6.187.idx" Filter="1" />
    <FileEntry Name="13301255444_v11.821.idx" Filter="1" />
    <FileEntry Name="13301255444_VIj.277.idx" Filter="1" />
    <FileEntry Name="13301255444_vWX.487.idx" Filter="1" />
    <FileEntry Name="13301255444_W5G.859.idx" Filter="1" />
    <FileEntry Name="13301255444_Wi4.951.idx" Filter="1" />
    <FileEntry Name="13301255444_Wiv.188.idx" Filter="1" />
    <FileEntry Name="13301255444_wQA.923.idx" Filter="1" />
    <FileEntry Name="13301255444_x80.995.idx" Filter="1" />
    <FileEntry Name="13301255444_XpH.995.idx" Filter="1" />
    <FileEntry Name="13301255444_Y8V.843.idx" Filter="1" />
    <FileEntry Name="13301255444_ydr.187.idx" Filter="1" />
    <FileEntry Name="13301255444_Ye4.179.idx" Filter="1" />
    <FileEntry Name="13301255444_yfT.943.idx" Filter="1" />
    <FileEntry Name="13301255444_YOu.669.idx" Filter="1" />
    <FileEntry Name="13301255444_YPU.91.idx" Filter="1" />
    <FileEntry Name="13301255444_yZc.375.idx" Filter="1" />
    <FileEntry Name="13301255444_Z9T.973.idx" Filter="1" />
    <FileEntry Name="13301255444_zFB.920.idx" Filter="1" />
    <FileEntry Name="13301255444_zHv.205.idx" Filter="1" />
    <FileEntry Name="13301255444_Zk8.429.idx" Filter="1" />
    <FileEntry Name="13301255444_zKs.819.idx" Filter="1" />
    <FileEntry Name="13301255444_ZTU.829.idx" Filter="1" />
    <FileEntry Name="13301255444_Zxy.779.idx" Filter="1" />
    <FileEntry Name="248820337440.idx" Filter="1" />
    <FileEntry Name="260796668440.idx" Filter="1" />
    <FileEntry Name="260862172440.idx" Filter="1" />
    <FileEntry Name="65885314440.idx" Filter="1" />
    <FileEntry Name="Bookmarks.xml" Filter="1" />
    <FileEntry Name="Breakpoints.xml" Filter="1" />
    <FileEntry Name="CompilerLogMetadata.xml" Filter="1" />
    <FileEntry Name="custom_body_variables.txt" Filter="1" />
    <FileEntry Name="data.zip" Filter="1" />
    <FileEntry Name="logfile.log" Filter="1" />
    <FileEntry Name="lrw_custom_body.h" Filter="1" />
    <FileEntry Name="mdrv.log" Filter="1" />
    <FileEntry Name="mdrvXyd.179.log" Filter="1" />
    <FileEntry Name="mdrvydq.41.log" Filter="1" />
    <FileEntry Name="mdrv_cmd.txt" Filter="1" />
    <FileEntry Name="options.txt" Filter="1" />
    <FileEntry Name="output.bak" Filter="1" />
    <FileEntry Name="output.txt" Filter="1" />
    <FileEntry Name="ReplaySummaryReport.xml" Filter="1" />
    <FileEntry Name="Script1.c.pickle" Filter="1" />
    <FileEntry Name="Script1.ci" Filter="1" />
    <FileEntry Name="Script1.prm.bak" Filter="1" />
    <FileEntry Name="Script1.sdf" Filter="1" />
    <FileEntry Name="ScriptUploadMetadata.xml" Filter="1" />
    <FileEntry Name="ThumbnailsCache.tmp" Filter="1" />
    <FileEntry Name="UserTasks.xml" Filter="1" />
    <FileEntry Name="data\" Filter="1" />
    <FileEntry Name="result1\" Filter="1" />
  </GeneralFiles>
</VugenScriptMetadata>